azcam_ds9/__init__.py
azcam_ds9/ds9display.py
azcam_ds9-22.3.2.dist-info/LICENSE
azcam_ds9-22.3.2.dist-info/WHEEL
azcam_ds9-22.3.2.dist-info/METADATA
azcam_ds9-22.3.2.dist-info/RECORD
