Metadata-Version: 2.1
Name: azcam-ds9
Version: 22.3.2
Summary: Azcam extension for SAO's ds9 image display
Keywords: ccd,imaging,astronomy,sensors
Author: Michael Lesser
Author-email: mlesser@arizona.edu
Requires-Dist: azcam
Requires-Dist: numpy
Requires-Dist: astropy
Project-URL: Documentation, https://mplesser.github.io/azcam/
Project-URL: Repository, https://github.com/mplesser/azcam-ds9/
